mypackage/__init__.py
mypackage/create.py
mypackage/labels.py
mypackage/modules.py
mypackage/upload.py
mypackage_falahgs-1.1.1.dist-info/LICENSE.txt
mypackage_falahgs-1.1.1.dist-info/METADATA
mypackage_falahgs-1.1.1.dist-info/WHEEL
mypackage_falahgs-1.1.1.dist-info/top_level.txt
mypackage_falahgs-1.1.1.dist-info/RECORD
