Metadata-Version: 2.1
Name: mypackage-falahgs
Version: 1.1.1
Summary: Create Object Segmentation Labels
Home-page: https://github.com/falahgs/
Author: Falahgs.G.Saleih
Author-email: falahgs07@gmail.com
License: MIT
Keywords: transformers,datasets
Classifier: Programming Language :: Python :: 3
Classifier: License :: OSI Approved :: MIT License
Classifier: Operating System :: OS Independent
Requires-Python: >=3.6
License-File: LICENSE.txt
Requires-Dist: roboflow
Requires-Dist: autodistill-grounded-sam ==0.1.1
